tangled_game_client/__init__.py
tangled_game_client/api/__init__.py
tangled_game_client/api/default_api.py
tangled_game_client/api_client.py
tangled_game_client/api_response.py
tangled_game_client/configuration.py
tangled_game_client/exceptions.py
tangled_game_client/models/__init__.py
tangled_game_client/models/create_game_request.py
tangled_game_client/models/create_game_response.py
tangled_game_client/models/error_response.py
tangled_game_client/models/get_game_state200_response.py
tangled_game_client/models/get_game_state200_response_state.py
tangled_game_client/models/get_legal_moves200_response.py
tangled_game_client/models/get_score200_response.py
tangled_game_client/models/get_score200_response_score.py
tangled_game_client/models/get_scorers200_response.py
tangled_game_client/models/join_game200_response.py
tangled_game_client/models/join_game_request.py
tangled_game_client/models/make_move200_response.py
tangled_game_client/models/make_move403_response.py
tangled_game_client/models/make_move_request.py
tangled_game_client/models/secret_create_game_request.py
tangled_game_client/models/secret_create_game_response.py
tangled_game_client/py.typed
tangled_game_client/rest.py
tangled_game_client-4.0.0.dist-info/METADATA
tangled_game_client-4.0.0.dist-info/WHEEL
tangled_game_client-4.0.0.dist-info/RECORD
